flatulent/__init__.py
flatulent/flatulent.py
flatulent-0.1.0.dist-info/LICENSE
flatulent-0.1.0.dist-info/METADATA
flatulent-0.1.0.dist-info/WHEEL
flatulent-0.1.0.dist-info/top_level.txt
flatulent-0.1.0.dist-info/RECORD
