Metadata-Version: 2.1
Name: flatulent
Version: 0.1.0
Summary: Flatulent é uma biblioteca de compressão que combina o algoritmo LZW com a codificação de Huffman para obter taxas de compressão eficientes. Voltada para ambientes sem threading, como Lambda Functions.
Home-page: https://github.com/vlaskz/flatulent
Author: Isaias Velasquez
Author-email: vlaskz@icloud.com
License: UNKNOWN
Platform: UNKNOWN
Classifier: License :: OSI Approved :: MIT License
Classifier: Programming Language :: Python :: 3
Classifier: Operating System :: OS Independent
License-File: LICENSE
